{
  "manifestVersion": "3.2",
  "admin": {
    "address": "0x0D230dDF8A849b6E3FF6b9Fd9aFF5A61F0243B22",
    "txHash": "0xcaa98a731a67c4a24e4c48f43d03c2cf88ac1141d624715873ac5f82f9c1350b"
  },
  "proxies": [
    {
      "address": "0xD45740aB9ec920bEdBD9BAb2E863519E59731941",
      "txHash": "0x41289015f9418a7dfa49349ef17a297b24d97e2bb5bcdc37bc80cf3f16169364",
      "kind": "transparent"
    },
    {
      "address": "0xc5fb34E3f69B18aBfbD17b2bBAbE8c9608D5779a",
      "txHash": "0x24f47b0b9400da57334d2d88d68b9321e0438b19fa12eeab315ab8cfc3bbfc28",
      "kind": "transparent"
    }
  ],
  "impls": {
    "734235f6362811925aafb6868c462707e1dfe7e0a32188e4ebea6a1c04a4f6e5": {
      "address": "0x89F795740c3f7CFE465fa854d330Dd89fad6770d",
      "txHash": "0x7414430bf57318f7628e2439b46618c6ffc380417c1e4a26720c7083946bbd19",
      "layout": {
        "storage": [
          {
            "contract": "Initializable",
            "label": "_initialized",
            "type": "t_bool",
            "src": "..\\@openzeppelin\\contracts-upgradeable\\proxy\\utils\\Initializable.sol:21"
          },
          {
            "contract": "Initializable",
            "label": "_initializing",
            "type": "t_bool",
            "src": "..\\@openzeppelin\\contracts-upgradeable\\proxy\\utils\\Initializable.sol:26"
          },
          {
            "contract": "ContextUpgradeable",
            "label": "__gap",
            "type": "t_array(t_uint256)50_storage",
            "src": "..\\@openzeppelin\\contracts-upgradeable\\utils\\ContextUpgradeable.sol:30"
          },
          {
            "contract": "ERC777Upgradeable",
            "label": "_balances",
            "type": "t_mapping(t_address,t_uint256)",
            "src": "..\\@openzeppelin\\contracts-upgradeable\\token\\ERC777\\ERC777Upgradeable.sol:34"
          },
          {
            "contract": "ERC777Upgradeable",
            "label": "_totalSupply",
            "type": "t_uint256",
            "src": "..\\@openzeppelin\\contracts-upgradeable\\token\\ERC777\\ERC777Upgradeable.sol:36"
          },
          {
            "contract": "ERC777Upgradeable",
            "label": "_name",
            "type": "t_string_storage",
            "src": "..\\@openzeppelin\\contracts-upgradeable\\token\\ERC777\\ERC777Upgradeable.sol:38"
          },
          {
            "contract": "ERC777Upgradeable",
            "label": "_symbol",
            "type": "t_string_storage",
            "src": "..\\@openzeppelin\\contracts-upgradeable\\token\\ERC777\\ERC777Upgradeable.sol:39"
          },
          {
            "contract": "ERC777Upgradeable",
            "label": "_defaultOperatorsArray",
            "type": "t_array(t_address)dyn_storage",
            "src": "..\\@openzeppelin\\contracts-upgradeable\\token\\ERC777\\ERC777Upgradeable.sol:45"
          },
          {
            "contract": "ERC777Upgradeable",
            "label": "_defaultOperators",
            "type": "t_mapping(t_address,t_bool)",
            "src": "..\\@openzeppelin\\contracts-upgradeable\\token\\ERC777\\ERC777Upgradeable.sol:48"
          },
          {
            "contract": "ERC777Upgradeable",
            "label": "_operators",
            "type": "t_mapping(t_address,t_mapping(t_address,t_bool))",
            "src": "..\\@openzeppelin\\contracts-upgradeable\\token\\ERC777\\ERC777Upgradeable.sol:51"
          },
          {
            "contract": "ERC777Upgradeable",
            "label": "_revokedDefaultOperators",
            "type": "t_mapping(t_address,t_mapping(t_address,t_bool))",
            "src": "..\\@openzeppelin\\contracts-upgradeable\\token\\ERC777\\ERC777Upgradeable.sol:52"
          },
          {
            "contract": "ERC777Upgradeable",
            "label": "_allowances",
            "type": "t_mapping(t_address,t_mapping(t_address,t_uint256))",
            "src": "..\\@openzeppelin\\contracts-upgradeable\\token\\ERC777\\ERC777Upgradeable.sol:55"
          },
          {
            "contract": "ERC777Upgradeable",
            "label": "__gap",
            "type": "t_array(t_uint256)41_storage",
            "src": "..\\@openzeppelin\\contracts-upgradeable\\token\\ERC777\\ERC777Upgradeable.sol:548"
          },
          {
            "contract": "ERC777PresetFixedSupplyUpgradeable",
            "label": "__gap",
            "type": "t_array(t_uint256)50_storage",
            "src": "..\\@openzeppelin\\contracts-upgradeable\\token\\ERC777\\presets\\ERC777PresetFixedSupplyUpgradeable.sol:51"
          },
          {
            "contract": "OwnableUpgradeable",
            "label": "_owner",
            "type": "t_address",
            "src": "..\\@openzeppelin\\contracts-upgradeable\\access\\OwnableUpgradeable.sol:21"
          },
          {
            "contract": "OwnableUpgradeable",
            "label": "__gap",
            "type": "t_array(t_uint256)49_storage",
            "src": "..\\@openzeppelin\\contracts-upgradeable\\access\\OwnableUpgradeable.sol:77"
          },
          {
            "contract": "SchnoodleV1",
            "label": "_totalSupply",
            "type": "t_uint256",
            "src": "..\\..\\..\\..\\..\\..\\..\\..\\C\\Users\\micro\\OneDrive - X-treem Software\\Development\\Projects\\Blockchain\\Schnoodle\\contracts\\SchnoodleV1.sol:11"
          },
          {
            "contract": "SchnoodleV1",
            "label": "_feePercent",
            "type": "t_uint256",
            "src": "..\\..\\..\\..\\..\\..\\..\\..\\C\\Users\\micro\\OneDrive - X-treem Software\\Development\\Projects\\Blockchain\\Schnoodle\\contracts\\SchnoodleV1.sol:12"
          },
          {
            "contract": "SchnoodleV1",
            "label": "_eleemosynary",
            "type": "t_address",
            "src": "..\\..\\..\\..\\..\\..\\..\\..\\C\\Users\\micro\\OneDrive - X-treem Software\\Development\\Projects\\Blockchain\\Schnoodle\\contracts\\SchnoodleV1.sol:13"
          },
          {
            "contract": "SchnoodleV1",
            "label": "_donationPercent",
            "type": "t_uint256",
            "src": "..\\..\\..\\..\\..\\..\\..\\..\\C\\Users\\micro\\OneDrive - X-treem Software\\Development\\Projects\\Blockchain\\Schnoodle\\contracts\\SchnoodleV1.sol:14"
          }
        ],
        "types": {
          "t_uint256": {
            "label": "uint256"
          },
          "t_address": {
            "label": "address"
          },
          "t_array(t_uint256)49_storage": {
            "label": "uint256[49]"
          },
          "t_array(t_uint256)50_storage": {
            "label": "uint256[50]"
          },
          "t_mapping(t_address,t_uint256)": {
            "label": "mapping(address => uint256)"
          },
          "t_string_storage": {
            "label": "string"
          },
          "t_array(t_address)dyn_storage": {
            "label": "address[]"
          },
          "t_mapping(t_address,t_bool)": {
            "label": "mapping(address => bool)"
          },
          "t_bool": {
            "label": "bool"
          },
          "t_mapping(t_address,t_mapping(t_address,t_bool))": {
            "label": "mapping(address => mapping(address => bool))"
          },
          "t_mapping(t_address,t_mapping(t_address,t_uint256))": {
            "label": "mapping(address => mapping(address => uint256))"
          },
          "t_array(t_uint256)41_storage": {
            "label": "uint256[41]"
          }
        }
      }
    },
    "8d010c30c3d800df7a1a979639e3b50e6ca29a42c56303e48d5fb3a3b200deeb": {
      "address": "0x0332B3a5E1fCA1Cd73e586f3dc98A62eBe5918eA",
      "txHash": "0x45313cfad281b9343e140eae041db09731ea28091ad59708dc9a342797d103f9",
      "layout": {
        "storage": [
          {
            "contract": "Initializable",
            "label": "_initialized",
            "type": "t_bool",
            "src": "..\\@openzeppelin\\contracts-upgradeable\\proxy\\utils\\Initializable.sol:21"
          },
          {
            "contract": "Initializable",
            "label": "_initializing",
            "type": "t_bool",
            "src": "..\\@openzeppelin\\contracts-upgradeable\\proxy\\utils\\Initializable.sol:26"
          },
          {
            "contract": "ContextUpgradeable",
            "label": "__gap",
            "type": "t_array(t_uint256)50_storage",
            "src": "..\\@openzeppelin\\contracts-upgradeable\\utils\\ContextUpgradeable.sol:30"
          },
          {
            "contract": "ERC777Upgradeable",
            "label": "_balances",
            "type": "t_mapping(t_address,t_uint256)",
            "src": "..\\@openzeppelin\\contracts-upgradeable\\token\\ERC777\\ERC777Upgradeable.sol:34"
          },
          {
            "contract": "ERC777Upgradeable",
            "label": "_totalSupply",
            "type": "t_uint256",
            "src": "..\\@openzeppelin\\contracts-upgradeable\\token\\ERC777\\ERC777Upgradeable.sol:36"
          },
          {
            "contract": "ERC777Upgradeable",
            "label": "_name",
            "type": "t_string_storage",
            "src": "..\\@openzeppelin\\contracts-upgradeable\\token\\ERC777\\ERC777Upgradeable.sol:38"
          },
          {
            "contract": "ERC777Upgradeable",
            "label": "_symbol",
            "type": "t_string_storage",
            "src": "..\\@openzeppelin\\contracts-upgradeable\\token\\ERC777\\ERC777Upgradeable.sol:39"
          },
          {
            "contract": "ERC777Upgradeable",
            "label": "_defaultOperatorsArray",
            "type": "t_array(t_address)dyn_storage",
            "src": "..\\@openzeppelin\\contracts-upgradeable\\token\\ERC777\\ERC777Upgradeable.sol:45"
          },
          {
            "contract": "ERC777Upgradeable",
            "label": "_defaultOperators",
            "type": "t_mapping(t_address,t_bool)",
            "src": "..\\@openzeppelin\\contracts-upgradeable\\token\\ERC777\\ERC777Upgradeable.sol:48"
          },
          {
            "contract": "ERC777Upgradeable",
            "label": "_operators",
            "type": "t_mapping(t_address,t_mapping(t_address,t_bool))",
            "src": "..\\@openzeppelin\\contracts-upgradeable\\token\\ERC777\\ERC777Upgradeable.sol:51"
          },
          {
            "contract": "ERC777Upgradeable",
            "label": "_revokedDefaultOperators",
            "type": "t_mapping(t_address,t_mapping(t_address,t_bool))",
            "src": "..\\@openzeppelin\\contracts-upgradeable\\token\\ERC777\\ERC777Upgradeable.sol:52"
          },
          {
            "contract": "ERC777Upgradeable",
            "label": "_allowances",
            "type": "t_mapping(t_address,t_mapping(t_address,t_uint256))",
            "src": "..\\@openzeppelin\\contracts-upgradeable\\token\\ERC777\\ERC777Upgradeable.sol:55"
          },
          {
            "contract": "ERC777Upgradeable",
            "label": "__gap",
            "type": "t_array(t_uint256)41_storage",
            "src": "..\\@openzeppelin\\contracts-upgradeable\\token\\ERC777\\ERC777Upgradeable.sol:548"
          },
          {
            "contract": "ERC777PresetFixedSupplyUpgradeable",
            "label": "__gap",
            "type": "t_array(t_uint256)50_storage",
            "src": "..\\@openzeppelin\\contracts-upgradeable\\token\\ERC777\\presets\\ERC777PresetFixedSupplyUpgradeable.sol:51"
          },
          {
            "contract": "OwnableUpgradeable",
            "label": "_owner",
            "type": "t_address",
            "src": "..\\@openzeppelin\\contracts-upgradeable\\access\\OwnableUpgradeable.sol:21"
          },
          {
            "contract": "OwnableUpgradeable",
            "label": "__gap",
            "type": "t_array(t_uint256)49_storage",
            "src": "..\\@openzeppelin\\contracts-upgradeable\\access\\OwnableUpgradeable.sol:77"
          },
          {
            "contract": "SchnoodleV2",
            "label": "_totalSupply",
            "type": "t_uint256",
            "src": "..\\..\\..\\..\\..\\..\\..\\..\\C\\Users\\micro\\OneDrive - X-treem Software\\Development\\Projects\\Blockchain\\Schnoodle\\contracts\\SchnoodleV2.sol:11"
          },
          {
            "contract": "SchnoodleV2",
            "label": "_feePercent",
            "type": "t_uint256",
            "src": "..\\..\\..\\..\\..\\..\\..\\..\\C\\Users\\micro\\OneDrive - X-treem Software\\Development\\Projects\\Blockchain\\Schnoodle\\contracts\\SchnoodleV2.sol:12"
          },
          {
            "contract": "SchnoodleV2",
            "label": "_eleemosynary",
            "type": "t_address",
            "src": "..\\..\\..\\..\\..\\..\\..\\..\\C\\Users\\micro\\OneDrive - X-treem Software\\Development\\Projects\\Blockchain\\Schnoodle\\contracts\\SchnoodleV2.sol:13"
          },
          {
            "contract": "SchnoodleV2",
            "label": "_donationPercent",
            "type": "t_uint256",
            "src": "..\\..\\..\\..\\..\\..\\..\\..\\C\\Users\\micro\\OneDrive - X-treem Software\\Development\\Projects\\Blockchain\\Schnoodle\\contracts\\SchnoodleV2.sol:14"
          }
        ],
        "types": {
          "t_uint256": {
            "label": "uint256"
          },
          "t_address": {
            "label": "address"
          },
          "t_array(t_uint256)49_storage": {
            "label": "uint256[49]"
          },
          "t_array(t_uint256)50_storage": {
            "label": "uint256[50]"
          },
          "t_mapping(t_address,t_uint256)": {
            "label": "mapping(address => uint256)"
          },
          "t_string_storage": {
            "label": "string"
          },
          "t_array(t_address)dyn_storage": {
            "label": "address[]"
          },
          "t_mapping(t_address,t_bool)": {
            "label": "mapping(address => bool)"
          },
          "t_bool": {
            "label": "bool"
          },
          "t_mapping(t_address,t_mapping(t_address,t_bool))": {
            "label": "mapping(address => mapping(address => bool))"
          },
          "t_mapping(t_address,t_mapping(t_address,t_uint256))": {
            "label": "mapping(address => mapping(address => uint256))"
          },
          "t_array(t_uint256)41_storage": {
            "label": "uint256[41]"
          }
        }
      }
    },
    "6a29bc9d0513785bf97e2566bcdb43e0973c4abce0fbb1dc3961236ff488298d": {
      "address": "0xD457578c9558b5C23F7A9DA070606A35D4df24Bf",
      "txHash": "0xb29c7e83c62d8f51ab695a93c713e20aa66836322fffe619739d622c2587164f",
      "layout": {
        "storage": [
          {
            "contract": "Initializable",
            "label": "_initialized",
            "type": "t_bool",
            "src": "..\\@openzeppelin\\contracts-upgradeable\\proxy\\utils\\Initializable.sol:21"
          },
          {
            "contract": "Initializable",
            "label": "_initializing",
            "type": "t_bool",
            "src": "..\\@openzeppelin\\contracts-upgradeable\\proxy\\utils\\Initializable.sol:26"
          },
          {
            "contract": "ContextUpgradeable",
            "label": "__gap",
            "type": "t_array(t_uint256)50_storage",
            "src": "..\\@openzeppelin\\contracts-upgradeable\\utils\\ContextUpgradeable.sol:30"
          },
          {
            "contract": "ERC777Upgradeable",
            "label": "_balances",
            "type": "t_mapping(t_address,t_uint256)",
            "src": "..\\@openzeppelin\\contracts-upgradeable\\token\\ERC777\\ERC777Upgradeable.sol:34"
          },
          {
            "contract": "ERC777Upgradeable",
            "label": "_totalSupply",
            "type": "t_uint256",
            "src": "..\\@openzeppelin\\contracts-upgradeable\\token\\ERC777\\ERC777Upgradeable.sol:36"
          },
          {
            "contract": "ERC777Upgradeable",
            "label": "_name",
            "type": "t_string_storage",
            "src": "..\\@openzeppelin\\contracts-upgradeable\\token\\ERC777\\ERC777Upgradeable.sol:38"
          },
          {
            "contract": "ERC777Upgradeable",
            "label": "_symbol",
            "type": "t_string_storage",
            "src": "..\\@openzeppelin\\contracts-upgradeable\\token\\ERC777\\ERC777Upgradeable.sol:39"
          },
          {
            "contract": "ERC777Upgradeable",
            "label": "_defaultOperatorsArray",
            "type": "t_array(t_address)dyn_storage",
            "src": "..\\@openzeppelin\\contracts-upgradeable\\token\\ERC777\\ERC777Upgradeable.sol:45"
          },
          {
            "contract": "ERC777Upgradeable",
            "label": "_defaultOperators",
            "type": "t_mapping(t_address,t_bool)",
            "src": "..\\@openzeppelin\\contracts-upgradeable\\token\\ERC777\\ERC777Upgradeable.sol:48"
          },
          {
            "contract": "ERC777Upgradeable",
            "label": "_operators",
            "type": "t_mapping(t_address,t_mapping(t_address,t_bool))",
            "src": "..\\@openzeppelin\\contracts-upgradeable\\token\\ERC777\\ERC777Upgradeable.sol:51"
          },
          {
            "contract": "ERC777Upgradeable",
            "label": "_revokedDefaultOperators",
            "type": "t_mapping(t_address,t_mapping(t_address,t_bool))",
            "src": "..\\@openzeppelin\\contracts-upgradeable\\token\\ERC777\\ERC777Upgradeable.sol:52"
          },
          {
            "contract": "ERC777Upgradeable",
            "label": "_allowances",
            "type": "t_mapping(t_address,t_mapping(t_address,t_uint256))",
            "src": "..\\@openzeppelin\\contracts-upgradeable\\token\\ERC777\\ERC777Upgradeable.sol:55"
          },
          {
            "contract": "ERC777Upgradeable",
            "label": "__gap",
            "type": "t_array(t_uint256)41_storage",
            "src": "..\\@openzeppelin\\contracts-upgradeable\\token\\ERC777\\ERC777Upgradeable.sol:548"
          },
          {
            "contract": "ERC777PresetFixedSupplyUpgradeable",
            "label": "__gap",
            "type": "t_array(t_uint256)50_storage",
            "src": "..\\@openzeppelin\\contracts-upgradeable\\token\\ERC777\\presets\\ERC777PresetFixedSupplyUpgradeable.sol:51"
          },
          {
            "contract": "OwnableUpgradeable",
            "label": "_owner",
            "type": "t_address",
            "src": "..\\@openzeppelin\\contracts-upgradeable\\access\\OwnableUpgradeable.sol:21"
          },
          {
            "contract": "OwnableUpgradeable",
            "label": "__gap",
            "type": "t_array(t_uint256)49_storage",
            "src": "..\\@openzeppelin\\contracts-upgradeable\\access\\OwnableUpgradeable.sol:77"
          },
          {
            "contract": "SchnoodleV3",
            "label": "_totalSupply",
            "type": "t_uint256",
            "src": "..\\..\\..\\..\\..\\..\\..\\..\\C\\Users\\micro\\OneDrive - X-treem Software\\Development\\Projects\\Blockchain\\Schnoodle\\contracts\\SchnoodleV3.sol:11"
          },
          {
            "contract": "SchnoodleV3",
            "label": "_feePercent",
            "type": "t_uint256",
            "src": "..\\..\\..\\..\\..\\..\\..\\..\\C\\Users\\micro\\OneDrive - X-treem Software\\Development\\Projects\\Blockchain\\Schnoodle\\contracts\\SchnoodleV3.sol:12"
          },
          {
            "contract": "SchnoodleV3",
            "label": "_eleemosynary",
            "type": "t_address",
            "src": "..\\..\\..\\..\\..\\..\\..\\..\\C\\Users\\micro\\OneDrive - X-treem Software\\Development\\Projects\\Blockchain\\Schnoodle\\contracts\\SchnoodleV3.sol:13"
          },
          {
            "contract": "SchnoodleV3",
            "label": "_donationPercent",
            "type": "t_uint256",
            "src": "..\\..\\..\\..\\..\\..\\..\\..\\C\\Users\\micro\\OneDrive - X-treem Software\\Development\\Projects\\Blockchain\\Schnoodle\\contracts\\SchnoodleV3.sol:14"
          }
        ],
        "types": {
          "t_uint256": {
            "label": "uint256"
          },
          "t_address": {
            "label": "address"
          },
          "t_array(t_uint256)49_storage": {
            "label": "uint256[49]"
          },
          "t_array(t_uint256)50_storage": {
            "label": "uint256[50]"
          },
          "t_mapping(t_address,t_uint256)": {
            "label": "mapping(address => uint256)"
          },
          "t_string_storage": {
            "label": "string"
          },
          "t_array(t_address)dyn_storage": {
            "label": "address[]"
          },
          "t_mapping(t_address,t_bool)": {
            "label": "mapping(address => bool)"
          },
          "t_bool": {
            "label": "bool"
          },
          "t_mapping(t_address,t_mapping(t_address,t_bool))": {
            "label": "mapping(address => mapping(address => bool))"
          },
          "t_mapping(t_address,t_mapping(t_address,t_uint256))": {
            "label": "mapping(address => mapping(address => uint256))"
          },
          "t_array(t_uint256)41_storage": {
            "label": "uint256[41]"
          }
        }
      }
    },
    "74d39e1b5732f80a534c945900df1062db7287a353f0194586be64c93691ee3e": {
      "address": "0x710b8C4E4F235241fEF5CAB3E30f8f5406774D4c",
      "txHash": "0x5c1772b9cedd128048e7e11679d7d02f285a1519187a2798d44d91bc25fa92c0",
      "layout": {
        "storage": [
          {
            "contract": "Initializable",
            "label": "_initialized",
            "type": "t_bool",
            "src": "..\\@openzeppelin\\contracts-upgradeable\\proxy\\utils\\Initializable.sol:21"
          },
          {
            "contract": "Initializable",
            "label": "_initializing",
            "type": "t_bool",
            "src": "..\\@openzeppelin\\contracts-upgradeable\\proxy\\utils\\Initializable.sol:26"
          },
          {
            "contract": "ContextUpgradeable",
            "label": "__gap",
            "type": "t_array(t_uint256)50_storage",
            "src": "..\\@openzeppelin\\contracts-upgradeable\\utils\\ContextUpgradeable.sol:30"
          },
          {
            "contract": "ERC777Upgradeable",
            "label": "_balances",
            "type": "t_mapping(t_address,t_uint256)",
            "src": "..\\@openzeppelin\\contracts-upgradeable\\token\\ERC777\\ERC777Upgradeable.sol:34"
          },
          {
            "contract": "ERC777Upgradeable",
            "label": "_totalSupply",
            "type": "t_uint256",
            "src": "..\\@openzeppelin\\contracts-upgradeable\\token\\ERC777\\ERC777Upgradeable.sol:36"
          },
          {
            "contract": "ERC777Upgradeable",
            "label": "_name",
            "type": "t_string_storage",
            "src": "..\\@openzeppelin\\contracts-upgradeable\\token\\ERC777\\ERC777Upgradeable.sol:38"
          },
          {
            "contract": "ERC777Upgradeable",
            "label": "_symbol",
            "type": "t_string_storage",
            "src": "..\\@openzeppelin\\contracts-upgradeable\\token\\ERC777\\ERC777Upgradeable.sol:39"
          },
          {
            "contract": "ERC777Upgradeable",
            "label": "_defaultOperatorsArray",
            "type": "t_array(t_address)dyn_storage",
            "src": "..\\@openzeppelin\\contracts-upgradeable\\token\\ERC777\\ERC777Upgradeable.sol:45"
          },
          {
            "contract": "ERC777Upgradeable",
            "label": "_defaultOperators",
            "type": "t_mapping(t_address,t_bool)",
            "src": "..\\@openzeppelin\\contracts-upgradeable\\token\\ERC777\\ERC777Upgradeable.sol:48"
          },
          {
            "contract": "ERC777Upgradeable",
            "label": "_operators",
            "type": "t_mapping(t_address,t_mapping(t_address,t_bool))",
            "src": "..\\@openzeppelin\\contracts-upgradeable\\token\\ERC777\\ERC777Upgradeable.sol:51"
          },
          {
            "contract": "ERC777Upgradeable",
            "label": "_revokedDefaultOperators",
            "type": "t_mapping(t_address,t_mapping(t_address,t_bool))",
            "src": "..\\@openzeppelin\\contracts-upgradeable\\token\\ERC777\\ERC777Upgradeable.sol:52"
          },
          {
            "contract": "ERC777Upgradeable",
            "label": "_allowances",
            "type": "t_mapping(t_address,t_mapping(t_address,t_uint256))",
            "src": "..\\@openzeppelin\\contracts-upgradeable\\token\\ERC777\\ERC777Upgradeable.sol:55"
          },
          {
            "contract": "ERC777Upgradeable",
            "label": "__gap",
            "type": "t_array(t_uint256)41_storage",
            "src": "..\\@openzeppelin\\contracts-upgradeable\\token\\ERC777\\ERC777Upgradeable.sol:548"
          },
          {
            "contract": "ERC777PresetFixedSupplyUpgradeable",
            "label": "__gap",
            "type": "t_array(t_uint256)50_storage",
            "src": "..\\@openzeppelin\\contracts-upgradeable\\token\\ERC777\\presets\\ERC777PresetFixedSupplyUpgradeable.sol:51"
          },
          {
            "contract": "OwnableUpgradeable",
            "label": "_owner",
            "type": "t_address",
            "src": "..\\@openzeppelin\\contracts-upgradeable\\access\\OwnableUpgradeable.sol:21"
          },
          {
            "contract": "OwnableUpgradeable",
            "label": "__gap",
            "type": "t_array(t_uint256)49_storage",
            "src": "..\\@openzeppelin\\contracts-upgradeable\\access\\OwnableUpgradeable.sol:77"
          },
          {
            "contract": "SchnoodleV4",
            "label": "_totalSupply",
            "type": "t_uint256",
            "src": "..\\project:\\contracts\\SchnoodleV4.sol:11"
          },
          {
            "contract": "SchnoodleV4",
            "label": "_feePercent",
            "type": "t_uint256",
            "src": "..\\project:\\contracts\\SchnoodleV4.sol:12"
          },
          {
            "contract": "SchnoodleV4",
            "label": "_eleemosynary",
            "type": "t_address",
            "src": "..\\project:\\contracts\\SchnoodleV4.sol:13"
          },
          {
            "contract": "SchnoodleV4",
            "label": "_donationPercent",
            "type": "t_uint256",
            "src": "..\\project:\\contracts\\SchnoodleV4.sol:14"
          }
        ],
        "types": {
          "t_uint256": {
            "label": "uint256"
          },
          "t_address": {
            "label": "address"
          },
          "t_array(t_uint256)49_storage": {
            "label": "uint256[49]"
          },
          "t_array(t_uint256)50_storage": {
            "label": "uint256[50]"
          },
          "t_mapping(t_address,t_uint256)": {
            "label": "mapping(address => uint256)"
          },
          "t_string_storage": {
            "label": "string"
          },
          "t_array(t_address)dyn_storage": {
            "label": "address[]"
          },
          "t_mapping(t_address,t_bool)": {
            "label": "mapping(address => bool)"
          },
          "t_bool": {
            "label": "bool"
          },
          "t_mapping(t_address,t_mapping(t_address,t_bool))": {
            "label": "mapping(address => mapping(address => bool))"
          },
          "t_mapping(t_address,t_mapping(t_address,t_uint256))": {
            "label": "mapping(address => mapping(address => uint256))"
          },
          "t_array(t_uint256)41_storage": {
            "label": "uint256[41]"
          }
        }
      }
    },
    "40068ae574c27894525af06dfe2b11fb54f2e82b3f0839995ab0df2b23b83f21": {
      "address": "0xAE9619CEABc21F7FBa931D98DCa7B25A09A51be3",
      "txHash": "0x6a0e9e5a915c86d63e8c06756e399f12291dbc0d0d795bd5124cbc0fd881941c",
      "layout": {
        "storage": [
          {
            "contract": "Initializable",
            "label": "_initialized",
            "type": "t_bool",
            "src": "..\\@openzeppelin\\contracts-upgradeable\\proxy\\utils\\Initializable.sol:21"
          },
          {
            "contract": "Initializable",
            "label": "_initializing",
            "type": "t_bool",
            "src": "..\\@openzeppelin\\contracts-upgradeable\\proxy\\utils\\Initializable.sol:26"
          },
          {
            "contract": "ContextUpgradeable",
            "label": "__gap",
            "type": "t_array(t_uint256)50_storage",
            "src": "..\\@openzeppelin\\contracts-upgradeable\\utils\\ContextUpgradeable.sol:30"
          },
          {
            "contract": "ERC777Upgradeable",
            "label": "_balances",
            "type": "t_mapping(t_address,t_uint256)",
            "src": "..\\@openzeppelin\\contracts-upgradeable\\token\\ERC777\\ERC777Upgradeable.sol:34"
          },
          {
            "contract": "ERC777Upgradeable",
            "label": "_totalSupply",
            "type": "t_uint256",
            "src": "..\\@openzeppelin\\contracts-upgradeable\\token\\ERC777\\ERC777Upgradeable.sol:36"
          },
          {
            "contract": "ERC777Upgradeable",
            "label": "_name",
            "type": "t_string_storage",
            "src": "..\\@openzeppelin\\contracts-upgradeable\\token\\ERC777\\ERC777Upgradeable.sol:38"
          },
          {
            "contract": "ERC777Upgradeable",
            "label": "_symbol",
            "type": "t_string_storage",
            "src": "..\\@openzeppelin\\contracts-upgradeable\\token\\ERC777\\ERC777Upgradeable.sol:39"
          },
          {
            "contract": "ERC777Upgradeable",
            "label": "_defaultOperatorsArray",
            "type": "t_array(t_address)dyn_storage",
            "src": "..\\@openzeppelin\\contracts-upgradeable\\token\\ERC777\\ERC777Upgradeable.sol:45"
          },
          {
            "contract": "ERC777Upgradeable",
            "label": "_defaultOperators",
            "type": "t_mapping(t_address,t_bool)",
            "src": "..\\@openzeppelin\\contracts-upgradeable\\token\\ERC777\\ERC777Upgradeable.sol:48"
          },
          {
            "contract": "ERC777Upgradeable",
            "label": "_operators",
            "type": "t_mapping(t_address,t_mapping(t_address,t_bool))",
            "src": "..\\@openzeppelin\\contracts-upgradeable\\token\\ERC777\\ERC777Upgradeable.sol:51"
          },
          {
            "contract": "ERC777Upgradeable",
            "label": "_revokedDefaultOperators",
            "type": "t_mapping(t_address,t_mapping(t_address,t_bool))",
            "src": "..\\@openzeppelin\\contracts-upgradeable\\token\\ERC777\\ERC777Upgradeable.sol:52"
          },
          {
            "contract": "ERC777Upgradeable",
            "label": "_allowances",
            "type": "t_mapping(t_address,t_mapping(t_address,t_uint256))",
            "src": "..\\@openzeppelin\\contracts-upgradeable\\token\\ERC777\\ERC777Upgradeable.sol:55"
          },
          {
            "contract": "ERC777Upgradeable",
            "label": "__gap",
            "type": "t_array(t_uint256)41_storage",
            "src": "..\\@openzeppelin\\contracts-upgradeable\\token\\ERC777\\ERC777Upgradeable.sol:548"
          },
          {
            "contract": "ERC777PresetFixedSupplyUpgradeable",
            "label": "__gap",
            "type": "t_array(t_uint256)50_storage",
            "src": "..\\@openzeppelin\\contracts-upgradeable\\token\\ERC777\\presets\\ERC777PresetFixedSupplyUpgradeable.sol:51"
          },
          {
            "contract": "OwnableUpgradeable",
            "label": "_owner",
            "type": "t_address",
            "src": "..\\@openzeppelin\\contracts-upgradeable\\access\\OwnableUpgradeable.sol:21"
          },
          {
            "contract": "OwnableUpgradeable",
            "label": "__gap",
            "type": "t_array(t_uint256)49_storage",
            "src": "..\\@openzeppelin\\contracts-upgradeable\\access\\OwnableUpgradeable.sol:77"
          },
          {
            "contract": "SchnoodleV5",
            "label": "_totalSupply",
            "type": "t_uint256",
            "src": "..\\project:\\contracts\\SchnoodleV5.sol:11"
          },
          {
            "contract": "SchnoodleV5",
            "label": "_feePercent",
            "type": "t_uint256",
            "src": "..\\project:\\contracts\\SchnoodleV5.sol:12"
          },
          {
            "contract": "SchnoodleV5",
            "label": "_eleemosynary",
            "type": "t_address",
            "src": "..\\project:\\contracts\\SchnoodleV5.sol:13"
          },
          {
            "contract": "SchnoodleV5",
            "label": "_donationPercent",
            "type": "t_uint256",
            "src": "..\\project:\\contracts\\SchnoodleV5.sol:14"
          }
        ],
        "types": {
          "t_uint256": {
            "label": "uint256"
          },
          "t_address": {
            "label": "address"
          },
          "t_array(t_uint256)49_storage": {
            "label": "uint256[49]"
          },
          "t_array(t_uint256)50_storage": {
            "label": "uint256[50]"
          },
          "t_mapping(t_address,t_uint256)": {
            "label": "mapping(address => uint256)"
          },
          "t_string_storage": {
            "label": "string"
          },
          "t_array(t_address)dyn_storage": {
            "label": "address[]"
          },
          "t_mapping(t_address,t_bool)": {
            "label": "mapping(address => bool)"
          },
          "t_bool": {
            "label": "bool"
          },
          "t_mapping(t_address,t_mapping(t_address,t_bool))": {
            "label": "mapping(address => mapping(address => bool))"
          },
          "t_mapping(t_address,t_mapping(t_address,t_uint256))": {
            "label": "mapping(address => mapping(address => uint256))"
          },
          "t_array(t_uint256)41_storage": {
            "label": "uint256[41]"
          }
        }
      }
    },
    "6e0cb351bbfc66b004f62fdaaf0bd69ca06e684aa4e7b1ef4854992552d76684": {
      "address": "0xBea9cd356c2d4afF8C3d4cD28E4002DDA551a859",
      "txHash": "0xe8e6b5d997b18ab8a490b7d622958ce7883148215eea54ba56abc5231902a089",
      "layout": {
        "storage": [
          {
            "contract": "Initializable",
            "label": "_initialized",
            "type": "t_bool",
            "src": "..\\@openzeppelin\\contracts-upgradeable\\proxy\\utils\\Initializable.sol:21"
          },
          {
            "contract": "Initializable",
            "label": "_initializing",
            "type": "t_bool",
            "src": "..\\@openzeppelin\\contracts-upgradeable\\proxy\\utils\\Initializable.sol:26"
          },
          {
            "contract": "ContextUpgradeable",
            "label": "__gap",
            "type": "t_array(t_uint256)50_storage",
            "src": "..\\@openzeppelin\\contracts-upgradeable\\utils\\ContextUpgradeable.sol:30"
          },
          {
            "contract": "ERC777Upgradeable",
            "label": "_balances",
            "type": "t_mapping(t_address,t_uint256)",
            "src": "..\\@openzeppelin\\contracts-upgradeable\\token\\ERC777\\ERC777Upgradeable.sol:34"
          },
          {
            "contract": "ERC777Upgradeable",
            "label": "_totalSupply",
            "type": "t_uint256",
            "src": "..\\@openzeppelin\\contracts-upgradeable\\token\\ERC777\\ERC777Upgradeable.sol:36"
          },
          {
            "contract": "ERC777Upgradeable",
            "label": "_name",
            "type": "t_string_storage",
            "src": "..\\@openzeppelin\\contracts-upgradeable\\token\\ERC777\\ERC777Upgradeable.sol:38"
          },
          {
            "contract": "ERC777Upgradeable",
            "label": "_symbol",
            "type": "t_string_storage",
            "src": "..\\@openzeppelin\\contracts-upgradeable\\token\\ERC777\\ERC777Upgradeable.sol:39"
          },
          {
            "contract": "ERC777Upgradeable",
            "label": "_defaultOperatorsArray",
            "type": "t_array(t_address)dyn_storage",
            "src": "..\\@openzeppelin\\contracts-upgradeable\\token\\ERC777\\ERC777Upgradeable.sol:45"
          },
          {
            "contract": "ERC777Upgradeable",
            "label": "_defaultOperators",
            "type": "t_mapping(t_address,t_bool)",
            "src": "..\\@openzeppelin\\contracts-upgradeable\\token\\ERC777\\ERC777Upgradeable.sol:48"
          },
          {
            "contract": "ERC777Upgradeable",
            "label": "_operators",
            "type": "t_mapping(t_address,t_mapping(t_address,t_bool))",
            "src": "..\\@openzeppelin\\contracts-upgradeable\\token\\ERC777\\ERC777Upgradeable.sol:51"
          },
          {
            "contract": "ERC777Upgradeable",
            "label": "_revokedDefaultOperators",
            "type": "t_mapping(t_address,t_mapping(t_address,t_bool))",
            "src": "..\\@openzeppelin\\contracts-upgradeable\\token\\ERC777\\ERC777Upgradeable.sol:52"
          },
          {
            "contract": "ERC777Upgradeable",
            "label": "_allowances",
            "type": "t_mapping(t_address,t_mapping(t_address,t_uint256))",
            "src": "..\\@openzeppelin\\contracts-upgradeable\\token\\ERC777\\ERC777Upgradeable.sol:55"
          },
          {
            "contract": "ERC777Upgradeable",
            "label": "__gap",
            "type": "t_array(t_uint256)41_storage",
            "src": "..\\@openzeppelin\\contracts-upgradeable\\token\\ERC777\\ERC777Upgradeable.sol:548"
          },
          {
            "contract": "ERC777PresetFixedSupplyUpgradeable",
            "label": "__gap",
            "type": "t_array(t_uint256)50_storage",
            "src": "..\\@openzeppelin\\contracts-upgradeable\\token\\ERC777\\presets\\ERC777PresetFixedSupplyUpgradeable.sol:51"
          },
          {
            "contract": "OwnableUpgradeable",
            "label": "_owner",
            "type": "t_address",
            "src": "..\\@openzeppelin\\contracts-upgradeable\\access\\OwnableUpgradeable.sol:21"
          },
          {
            "contract": "OwnableUpgradeable",
            "label": "__gap",
            "type": "t_array(t_uint256)49_storage",
            "src": "..\\@openzeppelin\\contracts-upgradeable\\access\\OwnableUpgradeable.sol:77"
          },
          {
            "contract": "SchnoodleV6",
            "label": "_totalSupply",
            "type": "t_uint256",
            "src": "..\\project:\\contracts\\SchnoodleV6.sol:12"
          },
          {
            "contract": "SchnoodleV6",
            "label": "_feeRate",
            "type": "t_uint256",
            "src": "..\\project:\\contracts\\SchnoodleV6.sol:13"
          },
          {
            "contract": "SchnoodleV6",
            "label": "_eleemosynary",
            "type": "t_address",
            "src": "..\\project:\\contracts\\SchnoodleV6.sol:14"
          },
          {
            "contract": "SchnoodleV6",
            "label": "_donationRate",
            "type": "t_uint256",
            "src": "..\\project:\\contracts\\SchnoodleV6.sol:15"
          },
          {
            "contract": "SchnoodleV6",
            "label": "_sellLimit",
            "type": "t_uint256",
            "src": "..\\project:\\contracts\\SchnoodleV6.sol:16"
          },
          {
            "contract": "SchnoodleV6",
            "label": "_sellQuota",
            "type": "t_struct(TokenMeter)12099_storage",
            "src": "..\\project:\\contracts\\SchnoodleV6.sol:17"
          }
        ],
        "types": {
          "t_uint256": {
            "label": "uint256"
          },
          "t_address": {
            "label": "address"
          },
          "t_struct(TokenMeter)12099_storage": {
            "label": "struct SchnoodleV6.TokenMeter",
            "members": [
              {
                "label": "blockMetric",
                "type": "t_uint256"
              },
              {
                "label": "amount",
                "type": "t_int256"
              }
            ]
          },
          "t_int256": {
            "label": "int256"
          },
          "t_array(t_uint256)49_storage": {
            "label": "uint256[49]"
          },
          "t_array(t_uint256)50_storage": {
            "label": "uint256[50]"
          },
          "t_mapping(t_address,t_uint256)": {
            "label": "mapping(address => uint256)"
          },
          "t_string_storage": {
            "label": "string"
          },
          "t_array(t_address)dyn_storage": {
            "label": "address[]"
          },
          "t_mapping(t_address,t_bool)": {
            "label": "mapping(address => bool)"
          },
          "t_bool": {
            "label": "bool"
          },
          "t_mapping(t_address,t_mapping(t_address,t_bool))": {
            "label": "mapping(address => mapping(address => bool))"
          },
          "t_mapping(t_address,t_mapping(t_address,t_uint256))": {
            "label": "mapping(address => mapping(address => uint256))"
          },
          "t_array(t_uint256)41_storage": {
            "label": "uint256[41]"
          }
        }
      }
    },
    "9084c1991fc8c5b4e11fb97078e3662e1215bb4e1b71f9e2c8235b8cff357cda": {
      "address": "0xBB6FeF2105606d6910E65ee30dF8d4c6d151AeE3",
      "txHash": "0x6dd6cb38098d02c8e4c755721628aedfa427e6aff6a00f385ad7427e5f1c4b7e",
      "layout": {
        "storage": [
          {
            "contract": "Initializable",
            "label": "_initialized",
            "type": "t_bool",
            "src": "..\\@openzeppelin\\contracts-upgradeable\\proxy\\utils\\Initializable.sol:21"
          },
          {
            "contract": "Initializable",
            "label": "_initializing",
            "type": "t_bool",
            "src": "..\\@openzeppelin\\contracts-upgradeable\\proxy\\utils\\Initializable.sol:26"
          },
          {
            "contract": "ContextUpgradeable",
            "label": "__gap",
            "type": "t_array(t_uint256)50_storage",
            "src": "..\\@openzeppelin\\contracts-upgradeable\\utils\\ContextUpgradeable.sol:30"
          },
          {
            "contract": "OwnableUpgradeable",
            "label": "_owner",
            "type": "t_address",
            "src": "..\\@openzeppelin\\contracts-upgradeable\\access\\OwnableUpgradeable.sol:21"
          },
          {
            "contract": "OwnableUpgradeable",
            "label": "__gap",
            "type": "t_array(t_uint256)49_storage",
            "src": "..\\@openzeppelin\\contracts-upgradeable\\access\\OwnableUpgradeable.sol:77"
          },
          {
            "contract": "SchnoodleFarmingV1",
            "label": "_schnoodle",
            "type": "t_address",
            "src": "..\\project:\\contracts\\SchnoodleFarmingV1.sol:12"
          },
          {
            "contract": "SchnoodleFarmingV1",
            "label": "_depositId",
            "type": "t_uint256",
            "src": "..\\project:\\contracts\\SchnoodleFarmingV1.sol:13"
          },
          {
            "contract": "SchnoodleFarmingV1",
            "label": "_accountDeposits",
            "type": "t_mapping(t_address,t_array(t_struct(Deposit)8304_storage)dyn_storage)",
            "src": "..\\project:\\contracts\\SchnoodleFarmingV1.sol:14"
          },
          {
            "contract": "SchnoodleFarmingV1",
            "label": "_accountUnbonds",
            "type": "t_mapping(t_address,t_array(t_struct(Unbond)8315_storage)dyn_storage)",
            "src": "..\\project:\\contracts\\SchnoodleFarmingV1.sol:15"
          },
          {
            "contract": "SchnoodleFarmingV1",
            "label": "_balances",
            "type": "t_mapping(t_address,t_uint256)",
            "src": "..\\project:\\contracts\\SchnoodleFarmingV1.sol:16"
          },
          {
            "contract": "SchnoodleFarmingV1",
            "label": "_totalTokens",
            "type": "t_uint256",
            "src": "..\\project:\\contracts\\SchnoodleFarmingV1.sol:17"
          },
          {
            "contract": "SchnoodleFarmingV1",
            "label": "_cumulativeTotal",
            "type": "t_uint256",
            "src": "..\\project:\\contracts\\SchnoodleFarmingV1.sol:18"
          },
          {
            "contract": "SchnoodleFarmingV1",
            "label": "_checkpointBlock",
            "type": "t_uint256",
            "src": "..\\project:\\contracts\\SchnoodleFarmingV1.sol:19"
          },
          {
            "contract": "SchnoodleFarmingV1",
            "label": "_totalDepositWeight",
            "type": "t_uint256",
            "src": "..\\project:\\contracts\\SchnoodleFarmingV1.sol:20"
          },
          {
            "contract": "SchnoodleFarmingV1",
            "label": "_sigmoidParams",
            "type": "t_struct(SigmoidParams)8320_storage",
            "src": "..\\project:\\contracts\\SchnoodleFarmingV1.sol:23"
          }
        ],
        "types": {
          "t_address": {
            "label": "address"
          },
          "t_uint256": {
            "label": "uint256"
          },
          "t_mapping(t_address,t_array(t_struct(Deposit)8304_storage)dyn_storage)": {
            "label": "mapping(address => struct SchnoodleFarmingV1.Deposit[])"
          },
          "t_array(t_struct(Deposit)8304_storage)dyn_storage": {
            "label": "struct SchnoodleFarmingV1.Deposit[]"
          },
          "t_struct(Deposit)8304_storage": {
            "label": "struct SchnoodleFarmingV1.Deposit",
            "members": [
              {
                "label": "id",
                "type": "t_uint256"
              },
              {
                "label": "amount",
                "type": "t_uint256"
              },
              {
                "label": "blockNumber",
                "type": "t_uint256"
              },
              {
                "label": "vestingBlocks",
                "type": "t_uint256"
              },
              {
                "label": "unbondingBlocks",
                "type": "t_uint256"
              },
              {
                "label": "multiplier",
                "type": "t_uint256"
              }
            ]
          },
          "t_mapping(t_address,t_array(t_struct(Unbond)8315_storage)dyn_storage)": {
            "label": "mapping(address => struct SchnoodleFarmingV1.Unbond[])"
          },
          "t_array(t_struct(Unbond)8315_storage)dyn_storage": {
            "label": "struct SchnoodleFarmingV1.Unbond[]"
          },
          "t_struct(Unbond)8315_storage": {
            "label": "struct SchnoodleFarmingV1.Unbond",
            "members": [
              {
                "label": "amount",
                "type": "t_uint256"
              },
              {
                "label": "expiryBlock",
                "type": "t_uint256"
              }
            ]
          },
          "t_mapping(t_address,t_uint256)": {
            "label": "mapping(address => uint256)"
          },
          "t_struct(SigmoidParams)8320_storage": {
            "label": "struct SchnoodleFarmingV1.SigmoidParams",
            "members": [
              {
                "label": "k",
                "type": "t_uint256"
              },
              {
                "label": "a",
                "type": "t_uint256"
              }
            ]
          },
          "t_array(t_uint256)49_storage": {
            "label": "uint256[49]"
          },
          "t_array(t_uint256)50_storage": {
            "label": "uint256[50]"
          },
          "t_bool": {
            "label": "bool"
          }
        }
      }
    },
    "32cf3f4910d026d13cc28e313453ed84109f24382dc2f6985b2791da3f8b837c": {
      "address": "0xF5Ac2132eD10fdA36143D0a3cF27940BFb3cD6d1",
      "txHash": "0xab1a1e404a460b31aa1870120ea64de081f8e3021da8064897d33a7264980ceb",
      "layout": {
        "storage": [
          {
            "contract": "Initializable",
            "label": "_initialized",
            "type": "t_bool",
            "src": "..\\@openzeppelin\\contracts-upgradeable\\proxy\\utils\\Initializable.sol:21"
          },
          {
            "contract": "Initializable",
            "label": "_initializing",
            "type": "t_bool",
            "src": "..\\@openzeppelin\\contracts-upgradeable\\proxy\\utils\\Initializable.sol:26"
          },
          {
            "contract": "ContextUpgradeable",
            "label": "__gap",
            "type": "t_array(t_uint256)50_storage",
            "src": "..\\@openzeppelin\\contracts-upgradeable\\utils\\ContextUpgradeable.sol:30"
          },
          {
            "contract": "ERC777Upgradeable",
            "label": "_balances",
            "type": "t_mapping(t_address,t_uint256)",
            "src": "..\\@openzeppelin\\contracts-upgradeable\\token\\ERC777\\ERC777Upgradeable.sol:34"
          },
          {
            "contract": "ERC777Upgradeable",
            "label": "_totalSupply",
            "type": "t_uint256",
            "src": "..\\@openzeppelin\\contracts-upgradeable\\token\\ERC777\\ERC777Upgradeable.sol:36"
          },
          {
            "contract": "ERC777Upgradeable",
            "label": "_name",
            "type": "t_string_storage",
            "src": "..\\@openzeppelin\\contracts-upgradeable\\token\\ERC777\\ERC777Upgradeable.sol:38"
          },
          {
            "contract": "ERC777Upgradeable",
            "label": "_symbol",
            "type": "t_string_storage",
            "src": "..\\@openzeppelin\\contracts-upgradeable\\token\\ERC777\\ERC777Upgradeable.sol:39"
          },
          {
            "contract": "ERC777Upgradeable",
            "label": "_defaultOperatorsArray",
            "type": "t_array(t_address)dyn_storage",
            "src": "..\\@openzeppelin\\contracts-upgradeable\\token\\ERC777\\ERC777Upgradeable.sol:45"
          },
          {
            "contract": "ERC777Upgradeable",
            "label": "_defaultOperators",
            "type": "t_mapping(t_address,t_bool)",
            "src": "..\\@openzeppelin\\contracts-upgradeable\\token\\ERC777\\ERC777Upgradeable.sol:48"
          },
          {
            "contract": "ERC777Upgradeable",
            "label": "_operators",
            "type": "t_mapping(t_address,t_mapping(t_address,t_bool))",
            "src": "..\\@openzeppelin\\contracts-upgradeable\\token\\ERC777\\ERC777Upgradeable.sol:51"
          },
          {
            "contract": "ERC777Upgradeable",
            "label": "_revokedDefaultOperators",
            "type": "t_mapping(t_address,t_mapping(t_address,t_bool))",
            "src": "..\\@openzeppelin\\contracts-upgradeable\\token\\ERC777\\ERC777Upgradeable.sol:52"
          },
          {
            "contract": "ERC777Upgradeable",
            "label": "_allowances",
            "type": "t_mapping(t_address,t_mapping(t_address,t_uint256))",
            "src": "..\\@openzeppelin\\contracts-upgradeable\\token\\ERC777\\ERC777Upgradeable.sol:55"
          },
          {
            "contract": "ERC777Upgradeable",
            "label": "__gap",
            "type": "t_array(t_uint256)41_storage",
            "src": "..\\@openzeppelin\\contracts-upgradeable\\token\\ERC777\\ERC777Upgradeable.sol:548"
          },
          {
            "contract": "ERC777PresetFixedSupplyUpgradeable",
            "label": "__gap",
            "type": "t_array(t_uint256)50_storage",
            "src": "..\\@openzeppelin\\contracts-upgradeable\\token\\ERC777\\presets\\ERC777PresetFixedSupplyUpgradeable.sol:51"
          },
          {
            "contract": "OwnableUpgradeable",
            "label": "_owner",
            "type": "t_address",
            "src": "..\\@openzeppelin\\contracts-upgradeable\\access\\OwnableUpgradeable.sol:21"
          },
          {
            "contract": "OwnableUpgradeable",
            "label": "__gap",
            "type": "t_array(t_uint256)49_storage",
            "src": "..\\@openzeppelin\\contracts-upgradeable\\access\\OwnableUpgradeable.sol:77"
          },
          {
            "contract": "SchnoodleV7Base",
            "label": "_totalSupply",
            "type": "t_uint256",
            "src": "..\\project:\\contracts\\imports\\SchnoodleV7Base.sol:12"
          },
          {
            "contract": "SchnoodleV7Base",
            "label": "_feeRate",
            "type": "t_uint256",
            "src": "..\\project:\\contracts\\imports\\SchnoodleV7Base.sol:13"
          },
          {
            "contract": "SchnoodleV7Base",
            "label": "_eleemosynaryAccount",
            "type": "t_address",
            "src": "..\\project:\\contracts\\imports\\SchnoodleV7Base.sol:14"
          },
          {
            "contract": "SchnoodleV7Base",
            "label": "_donationRate",
            "type": "t_uint256",
            "src": "..\\project:\\contracts\\imports\\SchnoodleV7Base.sol:15"
          },
          {
            "contract": "SchnoodleV7Base",
            "label": "_sellThreshold",
            "type": "t_uint256",
            "src": "..\\project:\\contracts\\imports\\SchnoodleV7Base.sol:16"
          },
          {
            "contract": "SchnoodleV7Base",
            "label": "_sellQuota",
            "type": "t_struct(TokenMeter)15040_storage",
            "src": "..\\project:\\contracts\\imports\\SchnoodleV7Base.sol:17"
          },
          {
            "contract": "SchnoodleV7Base",
            "label": "_rateEscalator",
            "type": "t_uint256",
            "src": "..\\project:\\contracts\\imports\\SchnoodleV7Base.sol:18"
          },
          {
            "contract": "ERC165Upgradeable",
            "label": "__gap",
            "type": "t_array(t_uint256)50_storage",
            "src": "..\\@openzeppelin\\contracts-upgradeable\\utils\\introspection\\ERC165Upgradeable.sol:35"
          },
          {
            "contract": "AccessControlUpgradeable",
            "label": "_roles",
            "type": "t_mapping(t_bytes32,t_struct(RoleData)81_storage)",
            "src": "..\\@openzeppelin\\contracts-upgradeable\\access\\AccessControlUpgradeable.sol:77"
          },
          {
            "contract": "AccessControlUpgradeable",
            "label": "__gap",
            "type": "t_array(t_uint256)49_storage",
            "src": "..\\@openzeppelin\\contracts-upgradeable\\access\\AccessControlUpgradeable.sol:259"
          },
          {
            "contract": "SchnoodleV7",
            "label": "_schnoodleFarming",
            "type": "t_address",
            "src": "..\\project:\\contracts\\SchnoodleV7.sol:11"
          },
          {
            "contract": "SchnoodleV7",
            "label": "_farmingFund",
            "type": "t_address",
            "src": "..\\project:\\contracts\\SchnoodleV7.sol:12"
          },
          {
            "contract": "SchnoodleV7",
            "label": "_sowRate",
            "type": "t_uint256",
            "src": "..\\project:\\contracts\\SchnoodleV7.sol:13"
          }
        ],
        "types": {
          "t_address": {
            "label": "address"
          },
          "t_uint256": {
            "label": "uint256"
          },
          "t_mapping(t_bytes32,t_struct(RoleData)81_storage)": {
            "label": "mapping(bytes32 => struct AccessControlUpgradeable.RoleData)"
          },
          "t_bytes32": {
            "label": "bytes32"
          },
          "t_struct(RoleData)81_storage": {
            "label": "struct AccessControlUpgradeable.RoleData",
            "members": [
              {
                "label": "members",
                "type": "t_mapping(t_address,t_bool)"
              },
              {
                "label": "adminRole",
                "type": "t_bytes32"
              }
            ]
          },
          "t_mapping(t_address,t_bool)": {
            "label": "mapping(address => bool)"
          },
          "t_bool": {
            "label": "bool"
          },
          "t_array(t_uint256)49_storage": {
            "label": "uint256[49]"
          },
          "t_array(t_uint256)50_storage": {
            "label": "uint256[50]"
          },
          "t_struct(TokenMeter)15040_storage": {
            "label": "struct SchnoodleV7Base.TokenMeter",
            "members": [
              {
                "label": "blockMetric",
                "type": "t_uint256"
              },
              {
                "label": "amount",
                "type": "t_int256"
              }
            ]
          },
          "t_int256": {
            "label": "int256"
          },
          "t_mapping(t_address,t_uint256)": {
            "label": "mapping(address => uint256)"
          },
          "t_string_storage": {
            "label": "string"
          },
          "t_array(t_address)dyn_storage": {
            "label": "address[]"
          },
          "t_mapping(t_address,t_mapping(t_address,t_bool))": {
            "label": "mapping(address => mapping(address => bool))"
          },
          "t_mapping(t_address,t_mapping(t_address,t_uint256))": {
            "label": "mapping(address => mapping(address => uint256))"
          },
          "t_array(t_uint256)41_storage": {
            "label": "uint256[41]"
          }
        }
      }
    },
    "71a3e8c7dd7811f0ff9bce4942f5193f1761be6f77bacba0b2e5ea93ddcc8a45": {
      "address": "0x8A43aa68442bA8B279793E65fB66aA1D969e4E5a",
      "txHash": "0x907bf72839dcb6bbbaba65339561d11e92afaa10995e3091a5a71019cdcd547d",
      "layout": {
        "storage": [
          {
            "contract": "Initializable",
            "label": "_initialized",
            "type": "t_bool",
            "src": "..\\@openzeppelin\\contracts-upgradeable\\proxy\\utils\\Initializable.sol:21"
          },
          {
            "contract": "Initializable",
            "label": "_initializing",
            "type": "t_bool",
            "src": "..\\@openzeppelin\\contracts-upgradeable\\proxy\\utils\\Initializable.sol:26"
          },
          {
            "contract": "ContextUpgradeable",
            "label": "__gap",
            "type": "t_array(t_uint256)50_storage",
            "src": "..\\@openzeppelin\\contracts-upgradeable\\utils\\ContextUpgradeable.sol:30"
          },
          {
            "contract": "OwnableUpgradeable",
            "label": "_owner",
            "type": "t_address",
            "src": "..\\@openzeppelin\\contracts-upgradeable\\access\\OwnableUpgradeable.sol:21"
          },
          {
            "contract": "OwnableUpgradeable",
            "label": "__gap",
            "type": "t_array(t_uint256)49_storage",
            "src": "..\\@openzeppelin\\contracts-upgradeable\\access\\OwnableUpgradeable.sol:77"
          },
          {
            "contract": "SchnoodleFarmingV2",
            "label": "_schnoodle",
            "type": "t_address",
            "src": "..\\project:\\contracts\\SchnoodleFarmingV2.sol:12"
          },
          {
            "contract": "SchnoodleFarmingV2",
            "label": "_depositId",
            "type": "t_uint256",
            "src": "..\\project:\\contracts\\SchnoodleFarmingV2.sol:13"
          },
          {
            "contract": "SchnoodleFarmingV2",
            "label": "_accountDeposits",
            "type": "t_mapping(t_address,t_array(t_struct(Deposit)9599_storage)dyn_storage)",
            "src": "..\\project:\\contracts\\SchnoodleFarmingV2.sol:14"
          },
          {
            "contract": "SchnoodleFarmingV2",
            "label": "_accountUnbonds",
            "type": "t_mapping(t_address,t_array(t_struct(Unbond)9610_storage)dyn_storage)",
            "src": "..\\project:\\contracts\\SchnoodleFarmingV2.sol:15"
          },
          {
            "contract": "SchnoodleFarmingV2",
            "label": "_balances",
            "type": "t_mapping(t_address,t_uint256)",
            "src": "..\\project:\\contracts\\SchnoodleFarmingV2.sol:16"
          },
          {
            "contract": "SchnoodleFarmingV2",
            "label": "_totalTokens",
            "type": "t_uint256",
            "src": "..\\project:\\contracts\\SchnoodleFarmingV2.sol:17"
          },
          {
            "contract": "SchnoodleFarmingV2",
            "label": "_cumulativeTotal",
            "type": "t_uint256",
            "src": "..\\project:\\contracts\\SchnoodleFarmingV2.sol:18"
          },
          {
            "contract": "SchnoodleFarmingV2",
            "label": "_checkpointBlock",
            "type": "t_uint256",
            "src": "..\\project:\\contracts\\SchnoodleFarmingV2.sol:19"
          },
          {
            "contract": "SchnoodleFarmingV2",
            "label": "_totalDepositWeight",
            "type": "t_uint256",
            "src": "..\\project:\\contracts\\SchnoodleFarmingV2.sol:20"
          },
          {
            "contract": "SchnoodleFarmingV2",
            "label": "_sigmoidParams",
            "type": "t_struct(SigmoidParams)9615_storage",
            "src": "..\\project:\\contracts\\SchnoodleFarmingV2.sol:23"
          },
          {
            "contract": "SchnoodleFarmingV2",
            "label": "_vestingBlocksFactor",
            "type": "t_uint256",
            "src": "..\\project:\\contracts\\SchnoodleFarmingV2.sol:25"
          },
          {
            "contract": "SchnoodleFarmingV2",
            "label": "_unbondingBlocksFactor",
            "type": "t_uint256",
            "src": "..\\project:\\contracts\\SchnoodleFarmingV2.sol:26"
          },
          {
            "contract": "SchnoodleFarmingV2",
            "label": "_maxUnbondingBlocks",
            "type": "t_uint256",
            "src": "..\\project:\\contracts\\SchnoodleFarmingV2.sol:27"
          }
        ],
        "types": {
          "t_address": {
            "label": "address"
          },
          "t_uint256": {
            "label": "uint256"
          },
          "t_mapping(t_address,t_array(t_struct(Deposit)9599_storage)dyn_storage)": {
            "label": "mapping(address => struct SchnoodleFarmingV2.Deposit[])"
          },
          "t_array(t_struct(Deposit)9599_storage)dyn_storage": {
            "label": "struct SchnoodleFarmingV2.Deposit[]"
          },
          "t_struct(Deposit)9599_storage": {
            "label": "struct SchnoodleFarmingV2.Deposit",
            "members": [
              {
                "label": "id",
                "type": "t_uint256"
              },
              {
                "label": "amount",
                "type": "t_uint256"
              },
              {
                "label": "blockNumber",
                "type": "t_uint256"
              },
              {
                "label": "vestingBlocks",
                "type": "t_uint256"
              },
              {
                "label": "unbondingBlocks",
                "type": "t_uint256"
              },
              {
                "label": "multiplier",
                "type": "t_uint256"
              }
            ]
          },
          "t_mapping(t_address,t_array(t_struct(Unbond)9610_storage)dyn_storage)": {
            "label": "mapping(address => struct SchnoodleFarmingV2.Unbond[])"
          },
          "t_array(t_struct(Unbond)9610_storage)dyn_storage": {
            "label": "struct SchnoodleFarmingV2.Unbond[]"
          },
          "t_struct(Unbond)9610_storage": {
            "label": "struct SchnoodleFarmingV2.Unbond",
            "members": [
              {
                "label": "amount",
                "type": "t_uint256"
              },
              {
                "label": "expiryBlock",
                "type": "t_uint256"
              }
            ]
          },
          "t_mapping(t_address,t_uint256)": {
            "label": "mapping(address => uint256)"
          },
          "t_struct(SigmoidParams)9615_storage": {
            "label": "struct SchnoodleFarmingV2.SigmoidParams",
            "members": [
              {
                "label": "k",
                "type": "t_uint256"
              },
              {
                "label": "a",
                "type": "t_uint256"
              }
            ]
          },
          "t_array(t_uint256)49_storage": {
            "label": "uint256[49]"
          },
          "t_array(t_uint256)50_storage": {
            "label": "uint256[50]"
          },
          "t_bool": {
            "label": "bool"
          }
        }
      }
    },
    "28fbfab444d55aebac277734ab8d265d1c023f326cd90322fbc44f9ae2c3e961": {
      "address": "0xe3491845cDbb15b4c3C9730595975eca12Db82e3",
      "txHash": "0xe9f80a25151cb72c0c54857678adccf87af85a01fa53a530fccc8e55c1c90ff5",
      "layout": {
        "storage": [
          {
            "contract": "Initializable",
            "label": "_initialized",
            "type": "t_bool",
            "src": "..\\@openzeppelin\\contracts-upgradeable\\proxy\\utils\\Initializable.sol:21"
          },
          {
            "contract": "Initializable",
            "label": "_initializing",
            "type": "t_bool",
            "src": "..\\@openzeppelin\\contracts-upgradeable\\proxy\\utils\\Initializable.sol:26"
          },
          {
            "contract": "ContextUpgradeable",
            "label": "__gap",
            "type": "t_array(t_uint256)50_storage",
            "src": "..\\@openzeppelin\\contracts-upgradeable\\utils\\ContextUpgradeable.sol:30"
          },
          {
            "contract": "ERC777Upgradeable",
            "label": "_balances",
            "type": "t_mapping(t_address,t_uint256)",
            "src": "..\\@openzeppelin\\contracts-upgradeable\\token\\ERC777\\ERC777Upgradeable.sol:34"
          },
          {
            "contract": "ERC777Upgradeable",
            "label": "_totalSupply",
            "type": "t_uint256",
            "src": "..\\@openzeppelin\\contracts-upgradeable\\token\\ERC777\\ERC777Upgradeable.sol:36"
          },
          {
            "contract": "ERC777Upgradeable",
            "label": "_name",
            "type": "t_string_storage",
            "src": "..\\@openzeppelin\\contracts-upgradeable\\token\\ERC777\\ERC777Upgradeable.sol:38"
          },
          {
            "contract": "ERC777Upgradeable",
            "label": "_symbol",
            "type": "t_string_storage",
            "src": "..\\@openzeppelin\\contracts-upgradeable\\token\\ERC777\\ERC777Upgradeable.sol:39"
          },
          {
            "contract": "ERC777Upgradeable",
            "label": "_defaultOperatorsArray",
            "type": "t_array(t_address)dyn_storage",
            "src": "..\\@openzeppelin\\contracts-upgradeable\\token\\ERC777\\ERC777Upgradeable.sol:45"
          },
          {
            "contract": "ERC777Upgradeable",
            "label": "_defaultOperators",
            "type": "t_mapping(t_address,t_bool)",
            "src": "..\\@openzeppelin\\contracts-upgradeable\\token\\ERC777\\ERC777Upgradeable.sol:48"
          },
          {
            "contract": "ERC777Upgradeable",
            "label": "_operators",
            "type": "t_mapping(t_address,t_mapping(t_address,t_bool))",
            "src": "..\\@openzeppelin\\contracts-upgradeable\\token\\ERC777\\ERC777Upgradeable.sol:51"
          },
          {
            "contract": "ERC777Upgradeable",
            "label": "_revokedDefaultOperators",
            "type": "t_mapping(t_address,t_mapping(t_address,t_bool))",
            "src": "..\\@openzeppelin\\contracts-upgradeable\\token\\ERC777\\ERC777Upgradeable.sol:52"
          },
          {
            "contract": "ERC777Upgradeable",
            "label": "_allowances",
            "type": "t_mapping(t_address,t_mapping(t_address,t_uint256))",
            "src": "..\\@openzeppelin\\contracts-upgradeable\\token\\ERC777\\ERC777Upgradeable.sol:55"
          },
          {
            "contract": "ERC777Upgradeable",
            "label": "__gap",
            "type": "t_array(t_uint256)41_storage",
            "src": "..\\@openzeppelin\\contracts-upgradeable\\token\\ERC777\\ERC777Upgradeable.sol:548"
          },
          {
            "contract": "ERC777PresetFixedSupplyUpgradeable",
            "label": "__gap",
            "type": "t_array(t_uint256)50_storage",
            "src": "..\\@openzeppelin\\contracts-upgradeable\\token\\ERC777\\presets\\ERC777PresetFixedSupplyUpgradeable.sol:51"
          },
          {
            "contract": "OwnableUpgradeable",
            "label": "_owner",
            "type": "t_address",
            "src": "..\\@openzeppelin\\contracts-upgradeable\\access\\OwnableUpgradeable.sol:21"
          },
          {
            "contract": "OwnableUpgradeable",
            "label": "__gap",
            "type": "t_array(t_uint256)49_storage",
            "src": "..\\@openzeppelin\\contracts-upgradeable\\access\\OwnableUpgradeable.sol:77"
          },
          {
            "contract": "SchnoodleV8Base",
            "label": "_totalSupply",
            "type": "t_uint256",
            "src": "..\\project:\\contracts\\imports\\SchnoodleV8Base.sol:12"
          },
          {
            "contract": "SchnoodleV8Base",
            "label": "_feeRate",
            "type": "t_uint256",
            "src": "..\\project:\\contracts\\imports\\SchnoodleV8Base.sol:13"
          },
          {
            "contract": "SchnoodleV8Base",
            "label": "_eleemosynaryAccount",
            "type": "t_address",
            "src": "..\\project:\\contracts\\imports\\SchnoodleV8Base.sol:14"
          },
          {
            "contract": "SchnoodleV8Base",
            "label": "_donationRate",
            "type": "t_uint256",
            "src": "..\\project:\\contracts\\imports\\SchnoodleV8Base.sol:15"
          },
          {
            "contract": "SchnoodleV8Base",
            "label": "_sellThreshold",
            "type": "t_uint256",
            "src": "..\\project:\\contracts\\imports\\SchnoodleV8Base.sol:16"
          },
          {
            "contract": "SchnoodleV8Base",
            "label": "_sellQuota",
            "type": "t_struct(TokenMeter)15893_storage",
            "src": "..\\project:\\contracts\\imports\\SchnoodleV8Base.sol:17"
          },
          {
            "contract": "SchnoodleV8Base",
            "label": "_rateEscalator",
            "type": "t_uint256",
            "src": "..\\project:\\contracts\\imports\\SchnoodleV8Base.sol:18"
          },
          {
            "contract": "ERC165Upgradeable",
            "label": "__gap",
            "type": "t_array(t_uint256)50_storage",
            "src": "..\\@openzeppelin\\contracts-upgradeable\\utils\\introspection\\ERC165Upgradeable.sol:35"
          },
          {
            "contract": "AccessControlUpgradeable",
            "label": "_roles",
            "type": "t_mapping(t_bytes32,t_struct(RoleData)81_storage)",
            "src": "..\\@openzeppelin\\contracts-upgradeable\\access\\AccessControlUpgradeable.sol:77"
          },
          {
            "contract": "AccessControlUpgradeable",
            "label": "__gap",
            "type": "t_array(t_uint256)49_storage",
            "src": "..\\@openzeppelin\\contracts-upgradeable\\access\\AccessControlUpgradeable.sol:259"
          },
          {
            "contract": "SchnoodleV8",
            "label": "_schnoodleFarming",
            "type": "t_address",
            "src": "..\\project:\\contracts\\SchnoodleV8.sol:11"
          },
          {
            "contract": "SchnoodleV8",
            "label": "_farmingFund",
            "type": "t_address",
            "src": "..\\project:\\contracts\\SchnoodleV8.sol:12"
          },
          {
            "contract": "SchnoodleV8",
            "label": "_sowRate",
            "type": "t_uint256",
            "src": "..\\project:\\contracts\\SchnoodleV8.sol:13"
          }
        ],
        "types": {
          "t_address": {
            "label": "address"
          },
          "t_uint256": {
            "label": "uint256"
          },
          "t_mapping(t_bytes32,t_struct(RoleData)81_storage)": {
            "label": "mapping(bytes32 => struct AccessControlUpgradeable.RoleData)"
          },
          "t_bytes32": {
            "label": "bytes32"
          },
          "t_struct(RoleData)81_storage": {
            "label": "struct AccessControlUpgradeable.RoleData",
            "members": [
              {
                "label": "members",
                "type": "t_mapping(t_address,t_bool)"
              },
              {
                "label": "adminRole",
                "type": "t_bytes32"
              }
            ]
          },
          "t_mapping(t_address,t_bool)": {
            "label": "mapping(address => bool)"
          },
          "t_bool": {
            "label": "bool"
          },
          "t_array(t_uint256)49_storage": {
            "label": "uint256[49]"
          },
          "t_array(t_uint256)50_storage": {
            "label": "uint256[50]"
          },
          "t_struct(TokenMeter)15893_storage": {
            "label": "struct SchnoodleV8Base.TokenMeter",
            "members": [
              {
                "label": "blockMetric",
                "type": "t_uint256"
              },
              {
                "label": "amount",
                "type": "t_int256"
              }
            ]
          },
          "t_int256": {
            "label": "int256"
          },
          "t_mapping(t_address,t_uint256)": {
            "label": "mapping(address => uint256)"
          },
          "t_string_storage": {
            "label": "string"
          },
          "t_array(t_address)dyn_storage": {
            "label": "address[]"
          },
          "t_mapping(t_address,t_mapping(t_address,t_bool))": {
            "label": "mapping(address => mapping(address => bool))"
          },
          "t_mapping(t_address,t_mapping(t_address,t_uint256))": {
            "label": "mapping(address => mapping(address => uint256))"
          },
          "t_array(t_uint256)41_storage": {
            "label": "uint256[41]"
          }
        }
      }
    },
    "79e62a8fe67c9b2e8ca1f5be258f1dd03df50f44ec6639380dc28d1298356302": {
      "address": "0xdD47F7CBB8b4DEf3c8EDA801BfaAc30796688338",
      "txHash": "0x9c697b6f6f4a8f27295baca4d3be5e1d8c0f7c10e8d405991db7cde1818b6d2b",
      "layout": {
        "storage": [
          {
            "contract": "Initializable",
            "label": "_initialized",
            "type": "t_uint8",
            "src": "..\\@schnoodle\\contracts-upgradeable\\proxy\\utils\\Initializable.sol:62",
            "retypedFrom": "bool"
          },
          {
            "contract": "Initializable",
            "label": "_initializing",
            "type": "t_bool",
            "src": "..\\@schnoodle\\contracts-upgradeable\\proxy\\utils\\Initializable.sol:67"
          },
          {
            "contract": "ContextUpgradeable",
            "label": "__gap",
            "type": "t_array(t_uint256)50_storage",
            "src": "..\\@schnoodle\\contracts-upgradeable\\utils\\ContextUpgradeable.sol:36"
          },
          {
            "contract": "ERC777Upgradeable",
            "label": "_balances",
            "type": "t_mapping(t_address,t_uint256)",
            "src": "..\\@schnoodle\\contracts-upgradeable\\token\\ERC777\\ERC777Upgradeable.sol:35"
          },
          {
            "contract": "ERC777Upgradeable",
            "label": "_totalSupply",
            "type": "t_uint256",
            "src": "..\\@schnoodle\\contracts-upgradeable\\token\\ERC777\\ERC777Upgradeable.sol:37"
          },
          {
            "contract": "ERC777Upgradeable",
            "label": "_name",
            "type": "t_string_storage",
            "src": "..\\@schnoodle\\contracts-upgradeable\\token\\ERC777\\ERC777Upgradeable.sol:39"
          },
          {
            "contract": "ERC777Upgradeable",
            "label": "_symbol",
            "type": "t_string_storage",
            "src": "..\\@schnoodle\\contracts-upgradeable\\token\\ERC777\\ERC777Upgradeable.sol:40"
          },
          {
            "contract": "ERC777Upgradeable",
            "label": "_defaultOperatorsArray",
            "type": "t_array(t_address)dyn_storage",
            "src": "..\\@schnoodle\\contracts-upgradeable\\token\\ERC777\\ERC777Upgradeable.sol:46"
          },
          {
            "contract": "ERC777Upgradeable",
            "label": "_defaultOperators",
            "type": "t_mapping(t_address,t_bool)",
            "src": "..\\@schnoodle\\contracts-upgradeable\\token\\ERC777\\ERC777Upgradeable.sol:49"
          },
          {
            "contract": "ERC777Upgradeable",
            "label": "_operators",
            "type": "t_mapping(t_address,t_mapping(t_address,t_bool))",
            "src": "..\\@schnoodle\\contracts-upgradeable\\token\\ERC777\\ERC777Upgradeable.sol:52"
          },
          {
            "contract": "ERC777Upgradeable",
            "label": "_revokedDefaultOperators",
            "type": "t_mapping(t_address,t_mapping(t_address,t_bool))",
            "src": "..\\@schnoodle\\contracts-upgradeable\\token\\ERC777\\ERC777Upgradeable.sol:53"
          },
          {
            "contract": "ERC777Upgradeable",
            "label": "_allowances",
            "type": "t_mapping(t_address,t_mapping(t_address,t_uint256))",
            "src": "..\\@schnoodle\\contracts-upgradeable\\token\\ERC777\\ERC777Upgradeable.sol:56"
          },
          {
            "contract": "ERC777Upgradeable",
            "label": "__gap",
            "type": "t_array(t_uint256)41_storage",
            "src": "..\\@schnoodle\\contracts-upgradeable\\token\\ERC777\\ERC777Upgradeable.sol:572"
          },
          {
            "contract": "ERC777PresetFixedSupplyUpgradeable",
            "label": "__gap",
            "type": "t_array(t_uint256)50_storage",
            "src": "..\\@schnoodle\\contracts-upgradeable\\token\\ERC777\\presets\\ERC777PresetFixedSupplyUpgradeable.sol:57"
          },
          {
            "contract": "OwnableUpgradeable",
            "label": "_owner",
            "type": "t_address",
            "src": "..\\@schnoodle\\contracts-upgradeable\\access\\OwnableUpgradeable.sol:22"
          },
          {
            "contract": "OwnableUpgradeable",
            "label": "__gap",
            "type": "t_array(t_uint256)49_storage",
            "src": "..\\@schnoodle\\contracts-upgradeable\\access\\OwnableUpgradeable.sol:87"
          },
          {
            "contract": "SchnoodleV9Base",
            "label": "_totalSupply",
            "type": "t_uint256",
            "src": "..\\project:\\contracts\\imports\\SchnoodleV9Base.sol:12"
          },
          {
            "contract": "SchnoodleV9Base",
            "label": "_feeRate",
            "type": "t_uint256",
            "src": "..\\project:\\contracts\\imports\\SchnoodleV9Base.sol:13"
          },
          {
            "contract": "SchnoodleV9Base",
            "label": "_eleemosynaryAccount",
            "type": "t_address",
            "src": "..\\project:\\contracts\\imports\\SchnoodleV9Base.sol:14"
          },
          {
            "contract": "SchnoodleV9Base",
            "label": "_donationRate",
            "type": "t_uint256",
            "src": "..\\project:\\contracts\\imports\\SchnoodleV9Base.sol:15"
          },
          {
            "contract": "SchnoodleV9Base",
            "label": "_sellThreshold",
            "type": "t_uint256",
            "src": "..\\project:\\contracts\\imports\\SchnoodleV9Base.sol:16"
          },
          {
            "contract": "SchnoodleV9Base",
            "label": "_sellQuota",
            "type": "t_struct(TokenMeter)19744_storage",
            "src": "..\\project:\\contracts\\imports\\SchnoodleV9Base.sol:17"
          },
          {
            "contract": "SchnoodleV9Base",
            "label": "_rateEscalator",
            "type": "t_uint256",
            "src": "..\\project:\\contracts\\imports\\SchnoodleV9Base.sol:18"
          },
          {
            "contract": "ERC165Upgradeable",
            "label": "__gap",
            "type": "t_array(t_uint256)50_storage",
            "src": "..\\@schnoodle\\contracts-upgradeable\\utils\\introspection\\ERC165Upgradeable.sol:41"
          },
          {
            "contract": "AccessControlUpgradeable",
            "label": "_roles",
            "type": "t_mapping(t_bytes32,t_struct(RoleData)2432_storage)",
            "src": "..\\@schnoodle\\contracts-upgradeable\\access\\AccessControlUpgradeable.sol:61"
          },
          {
            "contract": "AccessControlUpgradeable",
            "label": "__gap",
            "type": "t_array(t_uint256)49_storage",
            "src": "..\\@schnoodle\\contracts-upgradeable\\access\\AccessControlUpgradeable.sol:247"
          },
          {
            "contract": "SchnoodleV9",
            "label": "_schnoodleFarming",
            "type": "t_address",
            "src": "..\\project:\\contracts\\SchnoodleV9.sol:10"
          },
          {
            "contract": "SchnoodleV9",
            "label": "_farmingFund",
            "type": "t_address",
            "src": "..\\project:\\contracts\\SchnoodleV9.sol:11"
          },
          {
            "contract": "SchnoodleV9",
            "label": "_sowRate",
            "type": "t_uint256",
            "src": "..\\project:\\contracts\\SchnoodleV9.sol:12"
          },
          {
            "contract": "SchnoodleV9",
            "label": "_bridgeOwner",
            "type": "t_address",
            "src": "..\\project:\\contracts\\SchnoodleV9.sol:18"
          },
          {
            "contract": "SchnoodleV9",
            "label": "_tokensSent",
            "type": "t_mapping(t_address,t_mapping(t_uint256,t_uint256))",
            "src": "..\\project:\\contracts\\SchnoodleV9.sol:19"
          },
          {
            "contract": "SchnoodleV9",
            "label": "_tokensReceived",
            "type": "t_mapping(t_address,t_mapping(t_uint256,t_uint256))",
            "src": "..\\project:\\contracts\\SchnoodleV9.sol:20"
          },
          {
            "contract": "SchnoodleV9",
            "label": "_feesPaid",
            "type": "t_mapping(t_address,t_mapping(t_uint256,t_uint256))",
            "src": "..\\project:\\contracts\\SchnoodleV9.sol:21"
          }
        ],
        "types": {
          "t_address": {
            "label": "address"
          },
          "t_uint256": {
            "label": "uint256"
          },
          "t_mapping(t_address,t_mapping(t_uint256,t_uint256))": {
            "label": "mapping(address => mapping(uint256 => uint256))"
          },
          "t_mapping(t_uint256,t_uint256)": {
            "label": "mapping(uint256 => uint256)"
          },
          "t_mapping(t_bytes32,t_struct(RoleData)2432_storage)": {
            "label": "mapping(bytes32 => struct AccessControlUpgradeable.RoleData)"
          },
          "t_bytes32": {
            "label": "bytes32"
          },
          "t_struct(RoleData)2432_storage": {
            "label": "struct AccessControlUpgradeable.RoleData",
            "members": [
              {
                "label": "members",
                "type": "t_mapping(t_address,t_bool)"
              },
              {
                "label": "adminRole",
                "type": "t_bytes32"
              }
            ]
          },
          "t_mapping(t_address,t_bool)": {
            "label": "mapping(address => bool)"
          },
          "t_bool": {
            "label": "bool"
          },
          "t_array(t_uint256)49_storage": {
            "label": "uint256[49]"
          },
          "t_array(t_uint256)50_storage": {
            "label": "uint256[50]"
          },
          "t_struct(TokenMeter)19744_storage": {
            "label": "struct SchnoodleV9Base.TokenMeter",
            "members": [
              {
                "label": "blockMetric",
                "type": "t_uint256"
              },
              {
                "label": "amount",
                "type": "t_int256"
              }
            ]
          },
          "t_int256": {
            "label": "int256"
          },
          "t_mapping(t_address,t_uint256)": {
            "label": "mapping(address => uint256)"
          },
          "t_string_storage": {
            "label": "string"
          },
          "t_array(t_address)dyn_storage": {
            "label": "address[]"
          },
          "t_mapping(t_address,t_mapping(t_address,t_bool))": {
            "label": "mapping(address => mapping(address => bool))"
          },
          "t_mapping(t_address,t_mapping(t_address,t_uint256))": {
            "label": "mapping(address => mapping(address => uint256))"
          },
          "t_array(t_uint256)41_storage": {
            "label": "uint256[41]"
          },
          "t_uint8": {
            "label": "uint8"
          }
        }
      }
    },
    "6dc2c08b366d32eccc1601d09577e6a8855665682d2a8244dbd0a6895f66def7": {
      "address": "0xeAC2A259f3eBb8fD1097AECcaA62E73b6e43D5bF",
      "txHash": "0xbad56f7349921c2f98c9df688ea23d044af3728c619f5987e395bf4592448b94",
      "layout": {
        "storage": [
          {
            "contract": "Initializable",
            "label": "_initialized",
            "type": "t_uint8",
            "src": "..\\@schnoodle\\contracts-upgradeable\\proxy\\utils\\Initializable.sol:62",
            "retypedFrom": "bool"
          },
          {
            "contract": "Initializable",
            "label": "_initializing",
            "type": "t_bool",
            "src": "..\\@schnoodle\\contracts-upgradeable\\proxy\\utils\\Initializable.sol:67"
          },
          {
            "contract": "ContextUpgradeable",
            "label": "__gap",
            "type": "t_array(t_uint256)50_storage",
            "src": "..\\@schnoodle\\contracts-upgradeable\\utils\\ContextUpgradeable.sol:36"
          },
          {
            "contract": "ERC777Upgradeable",
            "label": "_balances",
            "type": "t_mapping(t_address,t_uint256)",
            "src": "..\\@schnoodle\\contracts-upgradeable\\token\\ERC777\\ERC777Upgradeable.sol:35"
          },
          {
            "contract": "ERC777Upgradeable",
            "label": "_totalSupply",
            "type": "t_uint256",
            "src": "..\\@schnoodle\\contracts-upgradeable\\token\\ERC777\\ERC777Upgradeable.sol:37"
          },
          {
            "contract": "ERC777Upgradeable",
            "label": "_name",
            "type": "t_string_storage",
            "src": "..\\@schnoodle\\contracts-upgradeable\\token\\ERC777\\ERC777Upgradeable.sol:39"
          },
          {
            "contract": "ERC777Upgradeable",
            "label": "_symbol",
            "type": "t_string_storage",
            "src": "..\\@schnoodle\\contracts-upgradeable\\token\\ERC777\\ERC777Upgradeable.sol:40"
          },
          {
            "contract": "ERC777Upgradeable",
            "label": "_defaultOperatorsArray",
            "type": "t_array(t_address)dyn_storage",
            "src": "..\\@schnoodle\\contracts-upgradeable\\token\\ERC777\\ERC777Upgradeable.sol:46"
          },
          {
            "contract": "ERC777Upgradeable",
            "label": "_defaultOperators",
            "type": "t_mapping(t_address,t_bool)",
            "src": "..\\@schnoodle\\contracts-upgradeable\\token\\ERC777\\ERC777Upgradeable.sol:49"
          },
          {
            "contract": "ERC777Upgradeable",
            "label": "_operators",
            "type": "t_mapping(t_address,t_mapping(t_address,t_bool))",
            "src": "..\\@schnoodle\\contracts-upgradeable\\token\\ERC777\\ERC777Upgradeable.sol:52"
          },
          {
            "contract": "ERC777Upgradeable",
            "label": "_revokedDefaultOperators",
            "type": "t_mapping(t_address,t_mapping(t_address,t_bool))",
            "src": "..\\@schnoodle\\contracts-upgradeable\\token\\ERC777\\ERC777Upgradeable.sol:53"
          },
          {
            "contract": "ERC777Upgradeable",
            "label": "_allowances",
            "type": "t_mapping(t_address,t_mapping(t_address,t_uint256))",
            "src": "..\\@schnoodle\\contracts-upgradeable\\token\\ERC777\\ERC777Upgradeable.sol:56"
          },
          {
            "contract": "ERC777Upgradeable",
            "label": "__gap",
            "type": "t_array(t_uint256)41_storage",
            "src": "..\\@schnoodle\\contracts-upgradeable\\token\\ERC777\\ERC777Upgradeable.sol:572"
          },
          {
            "contract": "ERC777PresetFixedSupplyUpgradeable",
            "label": "__gap",
            "type": "t_array(t_uint256)50_storage",
            "src": "..\\@schnoodle\\contracts-upgradeable\\token\\ERC777\\presets\\ERC777PresetFixedSupplyUpgradeable.sol:57"
          },
          {
            "contract": "OwnableUpgradeable",
            "label": "_owner",
            "type": "t_address",
            "src": "..\\@schnoodle\\contracts-upgradeable\\access\\OwnableUpgradeable.sol:22"
          },
          {
            "contract": "OwnableUpgradeable",
            "label": "__gap",
            "type": "t_array(t_uint256)49_storage",
            "src": "..\\@schnoodle\\contracts-upgradeable\\access\\OwnableUpgradeable.sol:87"
          },
          {
            "contract": "SchnoodleV9Base",
            "label": "_totalSupply",
            "type": "t_uint256",
            "src": "..\\project:\\contracts\\imports\\SchnoodleV9Base.sol:12"
          },
          {
            "contract": "SchnoodleV9Base",
            "label": "_feeRate",
            "type": "t_uint256",
            "src": "..\\project:\\contracts\\imports\\SchnoodleV9Base.sol:13"
          },
          {
            "contract": "SchnoodleV9Base",
            "label": "_eleemosynaryAccount",
            "type": "t_address",
            "src": "..\\project:\\contracts\\imports\\SchnoodleV9Base.sol:14"
          },
          {
            "contract": "SchnoodleV9Base",
            "label": "_donationRate",
            "type": "t_uint256",
            "src": "..\\project:\\contracts\\imports\\SchnoodleV9Base.sol:15"
          },
          {
            "contract": "SchnoodleV9Base",
            "label": "_sellThreshold",
            "type": "t_uint256",
            "src": "..\\project:\\contracts\\imports\\SchnoodleV9Base.sol:16"
          },
          {
            "contract": "SchnoodleV9Base",
            "label": "_sellQuota",
            "type": "t_struct(TokenMeter)19808_storage",
            "src": "..\\project:\\contracts\\imports\\SchnoodleV9Base.sol:17"
          },
          {
            "contract": "SchnoodleV9Base",
            "label": "_rateEscalator",
            "type": "t_uint256",
            "src": "..\\project:\\contracts\\imports\\SchnoodleV9Base.sol:18"
          },
          {
            "contract": "ERC165Upgradeable",
            "label": "__gap",
            "type": "t_array(t_uint256)50_storage",
            "src": "..\\@schnoodle\\contracts-upgradeable\\utils\\introspection\\ERC165Upgradeable.sol:41"
          },
          {
            "contract": "AccessControlUpgradeable",
            "label": "_roles",
            "type": "t_mapping(t_bytes32,t_struct(RoleData)2432_storage)",
            "src": "..\\@schnoodle\\contracts-upgradeable\\access\\AccessControlUpgradeable.sol:61"
          },
          {
            "contract": "AccessControlUpgradeable",
            "label": "__gap",
            "type": "t_array(t_uint256)49_storage",
            "src": "..\\@schnoodle\\contracts-upgradeable\\access\\AccessControlUpgradeable.sol:247"
          },
          {
            "contract": "SchnoodleV9",
            "label": "_schnoodleFarming",
            "type": "t_address",
            "src": "..\\project:\\contracts\\SchnoodleV9.sol:10"
          },
          {
            "contract": "SchnoodleV9",
            "label": "_farmingFund",
            "type": "t_address",
            "src": "..\\project:\\contracts\\SchnoodleV9.sol:11"
          },
          {
            "contract": "SchnoodleV9",
            "label": "_sowRate",
            "type": "t_uint256",
            "src": "..\\project:\\contracts\\SchnoodleV9.sol:12"
          },
          {
            "contract": "SchnoodleV9",
            "label": "_bridgeOwner",
            "type": "t_address",
            "src": "..\\project:\\contracts\\SchnoodleV9.sol:18"
          },
          {
            "contract": "SchnoodleV9",
            "label": "_tokensSent",
            "type": "t_mapping(t_address,t_mapping(t_uint256,t_uint256))",
            "src": "..\\project:\\contracts\\SchnoodleV9.sol:19"
          },
          {
            "contract": "SchnoodleV9",
            "label": "_tokensReceived",
            "type": "t_mapping(t_address,t_mapping(t_uint256,t_uint256))",
            "src": "..\\project:\\contracts\\SchnoodleV9.sol:20"
          },
          {
            "contract": "SchnoodleV9",
            "label": "_feesPaid",
            "type": "t_mapping(t_address,t_mapping(t_uint256,t_uint256))",
            "src": "..\\project:\\contracts\\SchnoodleV9.sol:21"
          }
        ],
        "types": {
          "t_address": {
            "label": "address"
          },
          "t_uint256": {
            "label": "uint256"
          },
          "t_mapping(t_address,t_mapping(t_uint256,t_uint256))": {
            "label": "mapping(address => mapping(uint256 => uint256))"
          },
          "t_mapping(t_uint256,t_uint256)": {
            "label": "mapping(uint256 => uint256)"
          },
          "t_mapping(t_bytes32,t_struct(RoleData)2432_storage)": {
            "label": "mapping(bytes32 => struct AccessControlUpgradeable.RoleData)"
          },
          "t_bytes32": {
            "label": "bytes32"
          },
          "t_struct(RoleData)2432_storage": {
            "label": "struct AccessControlUpgradeable.RoleData",
            "members": [
              {
                "label": "members",
                "type": "t_mapping(t_address,t_bool)"
              },
              {
                "label": "adminRole",
                "type": "t_bytes32"
              }
            ]
          },
          "t_mapping(t_address,t_bool)": {
            "label": "mapping(address => bool)"
          },
          "t_bool": {
            "label": "bool"
          },
          "t_array(t_uint256)49_storage": {
            "label": "uint256[49]"
          },
          "t_array(t_uint256)50_storage": {
            "label": "uint256[50]"
          },
          "t_struct(TokenMeter)19808_storage": {
            "label": "struct SchnoodleV9Base.TokenMeter",
            "members": [
              {
                "label": "blockMetric",
                "type": "t_uint256"
              },
              {
                "label": "amount",
                "type": "t_int256"
              }
            ]
          },
          "t_int256": {
            "label": "int256"
          },
          "t_mapping(t_address,t_uint256)": {
            "label": "mapping(address => uint256)"
          },
          "t_string_storage": {
            "label": "string"
          },
          "t_array(t_address)dyn_storage": {
            "label": "address[]"
          },
          "t_mapping(t_address,t_mapping(t_address,t_bool))": {
            "label": "mapping(address => mapping(address => bool))"
          },
          "t_mapping(t_address,t_mapping(t_address,t_uint256))": {
            "label": "mapping(address => mapping(address => uint256))"
          },
          "t_array(t_uint256)41_storage": {
            "label": "uint256[41]"
          },
          "t_uint8": {
            "label": "uint8"
          }
        }
      }
    }
  }
}
